src/__init__.py
src/run.py
src/omsutils/Swath.py
src/omsutils/__init__.py
src/omsutils/crop.py
src/omsutils/foo.py
src/omsutils/graphics.py
src/omsutils/grid.py
src/omsutils/runme.py
src/omsutils/fileio/__init__.py
src/omsutils/fileio/gpm.py
src/omsutils/fileio/tropics.py
omsutils-0.0.1.dist-info/LICENSE
omsutils-0.0.1.dist-info/METADATA
omsutils-0.0.1.dist-info/WHEEL
omsutils-0.0.1.dist-info/top_level.txt
omsutils-0.0.1.dist-info/RECORD
