Metadata-Version: 2.1
Name: omsutils
Version: 0.0.1
Summary: OMS Utilities
Home-page: http://pypi.python.org/pypi/PackageName/
Author: Johnny Hendricks
Author-email: Johnny Hendricks <johnny.hendricks@orbitalmicro.com>
License: LICENSE
Project-URL: Homepage, https://github.com/pypa/sampleproject
Project-URL: Bug Tracker, https://github.com/pypa/sampleproject/issues
Classifier: Programming Language :: Python :: 3
Classifier: License :: OSI Approved :: MIT License
Classifier: Operating System :: OS Independent
Requires-Python: >=3.7
License-File: LICENSE
Requires-Dist: pytest
